jupyterlab_codex/__init__.py
jupyterlab_codex/_version.py
jupyterlab_codex/handlers.py
jupyterlab_codex/labextension/build_log.json
jupyterlab_codex/labextension/package.json
jupyterlab_codex/labextension/schemas/jupyterlab-codex/package.json.orig
jupyterlab_codex/labextension/schemas/jupyterlab-codex/plugin.json
jupyterlab_codex/labextension/static/lib_index_js.9b79a0d85f0c69563594.js
jupyterlab_codex/labextension/static/lib_index_js.9b79a0d85f0c69563594.js.map
jupyterlab_codex/labextension/static/remoteEntry.978e7e9bc4b824189018.js
jupyterlab_codex/labextension/static/remoteEntry.978e7e9bc4b824189018.js.map
jupyterlab_codex/labextension/static/style.js
jupyterlab_codex/labextension/static/style_index_js.a601c5077947ec27bc1e.js
jupyterlab_codex/labextension/static/style_index_js.a601c5077947ec27bc1e.js.map
jupyterlab_codex/labextension/static/vendors-node_modules_css-loader_dist_runtime_api_js-node_modules_css-loader_dist_runtime_cssW-926fd9.e740d3aab9cf9b2147bf.js
jupyterlab_codex/labextension/static/vendors-node_modules_css-loader_dist_runtime_api_js-node_modules_css-loader_dist_runtime_cssW-926fd9.e740d3aab9cf9b2147bf.js.map
jupyterlab_codex-0.1.1.data/data/etc/jupyter/jupyter_notebook_config.d/jupyterlab_codex.json
jupyterlab_codex-0.1.1.data/data/etc/jupyter/jupyter_server_config.d/jupyterlab_codex.json
jupyterlab_codex-0.1.1.data/data/share/jupyter/labextensions/jupyterlab-codex/build_log.json
jupyterlab_codex-0.1.1.data/data/share/jupyter/labextensions/jupyterlab-codex/install.json
jupyterlab_codex-0.1.1.data/data/share/jupyter/labextensions/jupyterlab-codex/package.json
jupyterlab_codex-0.1.1.data/data/share/jupyter/labextensions/jupyterlab-codex/schemas/jupyterlab-codex/package.json.orig
jupyterlab_codex-0.1.1.data/data/share/jupyter/labextensions/jupyterlab-codex/schemas/jupyterlab-codex/plugin.json
jupyterlab_codex-0.1.1.data/data/share/jupyter/labextensions/jupyterlab-codex/static/lib_index_js.9b79a0d85f0c69563594.js
jupyterlab_codex-0.1.1.dist-info/LICENSE
jupyterlab_codex-0.1.1.dist-info/METADATA
jupyterlab_codex-0.1.1.dist-info/WHEEL
jupyterlab_codex-0.1.1.dist-info/top_level.txt
jupyterlab_codex-0.1.1.dist-info/RECORD
