Metadata-Version: 2.1
Name: jupyterlab-codex
Version: 0.1.1
Summary: JupyterLab extension that unlocks the power of OpenAI's Codex Model.
Home-page: https://github.com/lhr0909/jupyterlab-codex
Author: Simon Liang
Author-email: simon@x-tech.io
License: BSD-3-Clause
Keywords: Jupyter,JupyterLab,JupyterLab3
Platform: Linux
Platform: Mac OS X
Platform: Windows
Classifier: License :: OSI Approved :: BSD License
Classifier: Programming Language :: Python
Classifier: Programming Language :: Python :: 3
Classifier: Programming Language :: Python :: 3.6
Classifier: Programming Language :: Python :: 3.7
Classifier: Programming Language :: Python :: 3.8
Classifier: Programming Language :: Python :: 3.9
Classifier: Framework :: Jupyter
Requires-Python: >=3.6
License-File: LICENSE
Requires-Dist: openai
